odoo/addons/contract_operating_unit/README.rst
odoo/addons/contract_operating_unit/__init__.py
odoo/addons/contract_operating_unit/__manifest__.py
odoo/addons/contract_operating_unit/i18n/contract_operating_unit.pot
odoo/addons/contract_operating_unit/i18n/it.po
odoo/addons/contract_operating_unit/models/__init__.py
odoo/addons/contract_operating_unit/models/contract.py
odoo/addons/contract_operating_unit/readme/CONTRIBUTORS.md
odoo/addons/contract_operating_unit/readme/DESCRIPTION.md
odoo/addons/contract_operating_unit/readme/USAGE.md
odoo/addons/contract_operating_unit/security/contract_security.xml
odoo/addons/contract_operating_unit/static/description/icon.png
odoo/addons/contract_operating_unit/static/description/index.html
odoo/addons/contract_operating_unit/tests/__init__.py
odoo/addons/contract_operating_unit/tests/test_contract_operating_unit.py
odoo/addons/contract_operating_unit/views/contract_view.xml
odoo_addon_contract_operating_unit-17.0.1.1.0.dist-info/METADATA
odoo_addon_contract_operating_unit-17.0.1.1.0.dist-info/WHEEL
odoo_addon_contract_operating_unit-17.0.1.1.0.dist-info/top_level.txt
odoo_addon_contract_operating_unit-17.0.1.1.0.dist-info/RECORD
