Metadata-Version: 2.1
Name: odoo-addon-contract_operating_unit
Version: 17.0.1.1.0
Requires-Python: >=3.10
Requires-Dist: odoo-addon-account_operating_unit>=17.0dev,<17.1dev
Requires-Dist: odoo-addon-contract>=17.0dev,<17.1dev
Requires-Dist: odoo>=17.0a,<17.1dev
Summary: Contract Operating Unit
Home-page: https://github.com/OCA/operating-unit
License: AGPL-3
Author: ForgeFlow S.L., Odoo Community Association (OCA)
Author-email: support@odoo-community.org
Classifier: Programming Language :: Python
Classifier: Framework :: Odoo
Classifier: Framework :: Odoo :: 17.0
Classifier: License :: OSI Approved :: GNU Affero General Public License v3
